ks_qmt_market_api/./.gitignore
ks_qmt_market_api/./LICENSE.txt
ks_qmt_market_api/./README.en.md
ks_qmt_market_api/./README.md
ks_qmt_market_api/./__about__.py
ks_qmt_market_api/./__init__.py
ks_qmt_market_api/./ks_qmt_market_api.py
ks_qmt_market_api/./pyproject.toml
ks_qmt_market_api/./requirements.txt
ks_qmt_market_api/./setup.py
ks_qmt_market_api-0.0.5.dist-info/METADATA
ks_qmt_market_api-0.0.5.dist-info/WHEEL
ks_qmt_market_api-0.0.5.dist-info/licenses/LICENSE.txt
ks_qmt_market_api-0.0.5.dist-info/RECORD
